very_basic_auth/__init__.py
very_basic_auth/user_auth.py
very_basic_auth-0.0.2.dist-info/METADATA
very_basic_auth-0.0.2.dist-info/WHEEL
very_basic_auth-0.0.2.dist-info/top_level.txt
very_basic_auth-0.0.2.dist-info/RECORD
